dxplorer/__init__.py
dxplorer/core.py
dxplorer/impute.py
dxplorer/profiler.py
dxplorer/report.py
dxplorer/visualizer.py
dxplorer-0.1.0.dist-info/licenses/LICENSE
dxplorer-0.1.0.dist-info/METADATA
dxplorer-0.1.0.dist-info/WHEEL
dxplorer-0.1.0.dist-info/top_level.txt
dxplorer-0.1.0.dist-info/RECORD
