Metadata-Version: 2.4
Name: dxplorer
Version: 0.1.0
Summary: A Python package for quick data quality profiling with visualization and imputation suggestions
Home-page: https://github.com/talha-11-11/dxplorer
Author: Talha Sarfraz
Author-email: talhasarfraz29@gmail.com
Classifier: Programming Language :: Python :: 3
Classifier: License :: OSI Approved :: MIT License
Classifier: Operating System :: OS Independent
Requires-Python: >=3.6
License-File: LICENSE
Requires-Dist: pandas
Requires-Dist: seaborn
Requires-Dist: matplotlib
Dynamic: author
Dynamic: author-email
Dynamic: classifier
Dynamic: description
Dynamic: description-content-type
Dynamic: home-page
Dynamic: license-file
Dynamic: requires-dist
Dynamic: requires-python
Dynamic: summary
